optimise/__init__.py
optimise/gridplot.py
optimise/optimise.py
optimise/runs.py
optimise-0.1.0.data/data/etc/optimise/readme.md
optimise-0.1.0.data/data/etc/optimise/search.yaml
optimise-0.1.0.data/data/etc/optimise/version
optimise-0.1.0.dist-info/DESCRIPTION.rst
optimise-0.1.0.dist-info/METADATA
optimise-0.1.0.dist-info/RECORD
optimise-0.1.0.dist-info/WHEEL
optimise-0.1.0.dist-info/metadata.json
optimise-0.1.0.dist-info/top_level.txt
