Metadata-Version: 2.0
Name: optimise
Version: 0.1.0
Summary: Wrapper for hyperopt optimisation
Home-page: https://github.com/simonm3/optimise.git
Author: UNKNOWN
Author-email: UNKNOWN
License: UNKNOWN
Platform: UNKNOWN
Requires-Dist: PyYAML
Requires-Dist: hyperopt
Requires-Dist: ipython
Requires-Dist: logcon
Requires-Dist: matplotlib
Requires-Dist: numpy
Requires-Dist: pandas
